podenco/__init__.py
podenco/cli.py
podenco/podenco.py
podenco/domain/podcast.py
podenco/repositories/yaml_repository.py
podenco/serializers/podcast_serializer_rss.py
podenco/use_cases/podcast_generate.py
podenco/use_cases/podcast_load.py
podenco-0.0.2.dist-info/AUTHORS.rst
podenco-0.0.2.dist-info/LICENSE
podenco-0.0.2.dist-info/METADATA
podenco-0.0.2.dist-info/WHEEL
podenco-0.0.2.dist-info/entry_points.txt
podenco-0.0.2.dist-info/top_level.txt
podenco-0.0.2.dist-info/RECORD
