Metadata-Version: 2.1
Name: podenco
Version: 0.0.2
Summary: Static podcast generator.
Home-page: https://github.com/cristobalcl/podenco
Author: Cristóbal Carnero Liñán
Author-email: ccarnerolinan@gmail.com
License: MIT license
Keywords: podenco
Platform: UNKNOWN
Classifier: Development Status :: 2 - Pre-Alpha
Classifier: Intended Audience :: Developers
Classifier: License :: OSI Approved :: MIT License
Classifier: Natural Language :: English
Classifier: Programming Language :: Python :: 3
Classifier: Programming Language :: Python :: 3.6
Classifier: Programming Language :: Python :: 3.7
Requires-Dist: Click (>=6.0)
Requires-Dist: attrs (>=19.1.0)
Requires-Dist: feedgen (>=0.7.0)
Requires-Dist: pyyaml (>=5.1)
